{
    "name": "Chicken",
    "id": 10496,
    "isMembersOnly": false,
    "examine": "Yep. Definitely a chicken.",
    "releaseDate": "25 November 2020",
    "versionAnchor": "Gordon and Mary's Farm",
    "combatLevel": 1,
    "hitpoints": 3,
    "maxHit": [
        "0"
    ],
    "slayerExperience": 3.0,
    "slayerCategory": [
        "Birds"
    ],
    "usesSkill": [
        "Slayer"
    ],
    "assignedBy": [
        "TURTAEL",
        "SPRIA"
    ],
    "attackLevel": 1,
    "strengthLevel": 1,
    "defenceLevel": 1,
    "rangedLevel": 1,
    "magicLevel": 1,
    "attackBonuses": {
        "melee": -47,
        "strength": -42
    },
    "defenceBonuses": {
        "stab": -42,
        "slash": -42,
        "crush": -42,
        "magic": -42,
        "ranged": -42,
        "lightRanged": -42,
        "standardRanged": -42,
        "heavyRanged": -42
    },
    "immunities": {
        "poison": true,
        "venom": true
    },
    "attackStyle": [
        "Stab"
    ],
    "attackSpeed": 4,
    "size": 1
}