{
    "name": "Cyclops",
    "id": 2463,
    "isMembersOnly": false,
    "examine": "A one-eyed man eater.",
    "releaseDate": "13 June 2006",
    "versionAnchor": "Level 56",
    "combatLevel": 56,
    "hitpoints": 75,
    "maxHit": [
        "6"
    ],
    "slayerExperience": 75.0,
    "slayerCategory": [
        "Hill Giants"
    ],
    "usesSkill": [
        "Slayer"
    ],
    "assignedBy": [
        "MAZCHNA",
        "VANNAKA"
    ],
    "attackLevel": 47,
    "strengthLevel": 50,
    "defenceLevel": 26,
    "rangedLevel": 1,
    "magicLevel": 1,
    "immunities": {
        "burn": true
    },
    "attackStyle": [
        "Crush"
    ],
    "attackSpeed": 4,
    "size": 2
}