{
    "name": "Sir Lancelot",
    "id": 4344,
    "isMembersOnly": false,
    "examine": "One of the Knights of the Round Table.",
    "releaseDate": "24 July 2007",
    "combatLevel": 127,
    "hitpoints": 115,
    "maxHit": [
        "23"
    ],
    "usesSkill": [
    ],
    "attackLevel": 110,
    "strengthLevel": 110,
    "defenceLevel": 110,
    "rangedLevel": 1,
    "magicLevel": 1,
    "attackBonuses": {
        "melee": 60,
        "strength": 60
    },
    "defenceBonuses": {
        "stab": 300,
        "slash": 85,
        "crush": 300
    },
    "immunities": {
        "venom": true
    },
    "attackStyle": [
        "Crush"
    ],
    "attackSpeed": 4,
    "experienceBonus": 17.5,
    "size": 1
}