{
    "name": "Corrupted scythe of vitur",
    "id": 28543,
    "members": false,
    "examine": "A powerful scythe.",
    "value": 250000,
    "weight": 3.175,
    "equipment": {
        "stabAttack": 56,
        "slashAttack": 88,
        "crushAttack": 24,
        "magicAttack": -6,
        "stabDefence": -2,
        "slashDefence": 7,
        "crushDefence": 8,
        "strength": 60,
        "slot": "WEAPON",
        "attackSpeed": 5,
        "attackRange": 1,
        "combatStyle": "SCYTHE"
    }
}